pytest_allure_dsl.py
pytest_allure_dsl-1.0.0.dist-info/METADATA
pytest_allure_dsl-1.0.0.dist-info/WHEEL
pytest_allure_dsl-1.0.0.dist-info/top_level.txt
pytest_allure_dsl-1.0.0.dist-info/RECORD
