Metadata-Version: 2.1
Name: pytest-allure-dsl
Version: 1.0.0
Summary: pytest plugin to test case doc string dls instructions
Home-page: https://github.com/trifonovmixail/pytest-allure-dsl
Author: Mikhail Trifonov
Author-email: trifonov.net@gmail.com
License: UNKNOWN
Keywords: py.test pytest allure dsl
Platform: UNKNOWN
Classifier: Development Status :: 4 - Beta
Classifier: Framework :: Pytest
Classifier: Intended Audience :: Developers
Classifier: Operating System :: POSIX
Classifier: Operating System :: Microsoft :: Windows
Classifier: Operating System :: MacOS :: MacOS X
Classifier: Topic :: Software Development :: Quality Assurance
Classifier: Topic :: Software Development :: Testing
Classifier: Topic :: Utilities
Classifier: Programming Language :: Python :: 2.7
Classifier: Programming Language :: Python :: 3.0
Classifier: Programming Language :: Python :: 3.5
Classifier: Programming Language :: Python :: 3.6
Classifier: Programming Language :: Python :: 3.7
Classifier: Programming Language :: Python :: Implementation :: CPython
Requires-Dist: wheel
Requires-Dist: pytest
Requires-Dist: allure-pytest (>=2.8.18)
Requires-Dist: PyYAML
Requires-Dist: future
